{
  "schema_version": "1.1",
  "timestamp": "20251010_140859",
  "event": "clean_markdown",
  "items": [
    "2435_merged_medical_records.cleaned.md",
    "2404_merged_medical_records.cleaned.md",
    "2405_merged_medical_records.cleaned.md",
    "2407_merged_medical_records.cleaned.md",
    "2459_merged_medical_records.cleaned.md",
    "2463_merged_medical_records.cleaned.md",
    "2413_merged_medical_records.cleaned.md",
    "2414_merged_medical_records.cleaned.md",
    "2452_merged_medical_records.cleaned.md",
    "2458_merged_medical_records.cleaned.md",
    "2447_merged_medical_records.cleaned.md",
    "2428_merged_medical_records.cleaned.md",
    "2406_merged_medical_records.cleaned.md",
    "2467_merged_medical_records.cleaned.md",
    "2465_merged_medical_records.cleaned.md",
    "2455_merged_medical_records.cleaned.md",
    "2442_merged_medical_records.cleaned.md",
    "2409_merged_medical_records.cleaned.md",
    "2430_merged_medical_records.cleaned.md",
    "2423_merged_medical_records.cleaned.md",
    "2450_merged_medical_records.cleaned.md",
    "2454_merged_medical_records.cleaned.md",
    "2456_merged_medical_records.cleaned.md",
    "2411_merged_medical_records.cleaned.md",
    "2453_merged_medical_records.cleaned.md",
    "2437_merged_medical_records.cleaned.md",
    "2439_merged_medical_records.cleaned.md",
    "2431_merged_medical_records.cleaned.md",
    "2441_merged_medical_records.cleaned.md",
    "2466_merged_medical_records.cleaned.md",
    "2448_merged_medical_records.cleaned.md",
    "2438_merged_medical_records.cleaned.md",
    "2432_merged_medical_records.cleaned.md",
    "2434_merged_medical_records.cleaned.md",
    "2402_merged_medical_records.cleaned.md",
    "2461_merged_medical_records.cleaned.md",
    "2446_merged_medical_records.cleaned.md",
    "2460_merged_medical_records.cleaned.md",
    "2445_merged_medical_records.cleaned.md",
    "2403_merged_medical_records.cleaned.md",
    "2436_merged_medical_records.cleaned.md",
    "2462_merged_medical_records.cleaned.md",
    "2410_merged_medical_records.cleaned.md",
    "2449_merged_medical_records.cleaned.md",
    "2433_merged_medical_records.cleaned.md",
    "2420_merged_medical_records.cleaned.md",
    "2417_merged_medical_records.cleaned.md",
    "2416_merged_medical_records.cleaned.md",
    "2444_merged_medical_records.cleaned.md",
    "2464_merged_medical_records.cleaned.md",
    "2408_merged_medical_records.cleaned.md",
    "2457_merged_medical_records.cleaned.md",
    "2426_merged_medical_records.cleaned.md",
    "2440_merged_medical_records.cleaned.md",
    "2415_merged_medical_records.cleaned.md",
    "2401_merged_medical_records.cleaned.md",
    "2418_merged_medical_records.cleaned.md",
    "2427_merged_medical_records.cleaned.md",
    "2443_merged_medical_records.cleaned.md",
    "2503_merged_medical_records.cleaned.md",
    "2424_merged_medical_records.cleaned.md",
    "2425_merged_medical_records.cleaned.md",
    "2422_merged_medical_records.cleaned.md",
    "2421_merged_medical_records.cleaned.md",
    "2419_merged_medical_records.cleaned.md",
    "2429_merged_medical_records.cleaned.md",
    "2412_merged_medical_records.cleaned.md",
    "2451_merged_medical_records.cleaned.md"
  ],
  "errors": [],
  "count_items": 68,
  "count_errors": 0,
  "details": {}
}